edition/VERSION
edition/__init__.py
edition/__main__.py
edition/cli.py
edition/html_renderer.py
edition/metadata.py
edition/pre_html_renderer.py
edition/py.typed
edition/exceptions/__init__.py
edition/exceptions/edition_error.py
edition/exceptions/no_press_error.py
edition/exceptions/py.typed
edition/html/__init__.py
edition/html/document.html
edition/html/py.typed
edition/html/style.css
edition/presses/__init__.py
edition/presses/html.py
edition/presses/markdown.py
edition/presses/press.py
edition/presses/py.typed
edition/tasks/__init__.py
edition/tasks/arguments.py
edition/tasks/press.py
edition/tasks/py.typed
edition-1.0.0a14.dist-info/LICENSE
edition-1.0.0a14.dist-info/METADATA
edition-1.0.0a14.dist-info/WHEEL
edition-1.0.0a14.dist-info/entry_points.txt
edition-1.0.0a14.dist-info/top_level.txt
edition-1.0.0a14.dist-info/RECORD
