Metadata-Version: 2.1
Name: edition
Version: 1.0.0a14
Summary: Creates beautiful HTML and Markdown editions of your documentation
Home-page: https://github.com/cariad/edition
Author: Cariad Eccleston
Author-email: cariad@cariad.earth
License: MIT
Platform: UNKNOWN
Classifier: Development Status :: 3 - Alpha
Classifier: Environment :: Console
Classifier: License :: OSI Approved :: MIT License
Classifier: Natural Language :: English
Classifier: Operating System :: POSIX :: Linux
Classifier: Programming Language :: Python :: 3 :: Only
Classifier: Programming Language :: Python :: 3.10
Classifier: Programming Language :: Python :: 3.8
Classifier: Programming Language :: Python :: 3.9
Classifier: Topic :: Utilities
Classifier: Typing :: Typed
Requires-Python: >=3.8
License-File: LICENSE
Requires-Dist: cline (~=1.1)
Requires-Dist: comprehemd (==1.0.0a4)
Requires-Dist: dinject (==1.3.0a4)
Requires-Dist: doutline (==1.0.0a3)
Requires-Dist: markdown (~=3.3.4)
Requires-Dist: pygments (~=2.10)
Requires-Dist: python-frontmatter (~=1.0)
